odoo8_addon_mail_sent-8.0.1.0.0.99.dev13-py2.7-nspkg.pth
odoo8_addon_mail_sent-8.0.1.0.0.99.dev13.dist-info/DESCRIPTION.rst
odoo8_addon_mail_sent-8.0.1.0.0.99.dev13.dist-info/METADATA
odoo8_addon_mail_sent-8.0.1.0.0.99.dev13.dist-info/RECORD
odoo8_addon_mail_sent-8.0.1.0.0.99.dev13.dist-info/WHEEL
odoo8_addon_mail_sent-8.0.1.0.0.99.dev13.dist-info/metadata.json
odoo8_addon_mail_sent-8.0.1.0.0.99.dev13.dist-info/namespace_packages.txt
odoo8_addon_mail_sent-8.0.1.0.0.99.dev13.dist-info/top_level.txt
odoo_addons/mail_sent/README.rst
odoo_addons/mail_sent/__init__.py
odoo_addons/mail_sent/__openerp__.py
odoo_addons/mail_sent/i18n/ca.po
odoo_addons/mail_sent/i18n/de.po
odoo_addons/mail_sent/i18n/el_GR.po
odoo_addons/mail_sent/i18n/es.po
odoo_addons/mail_sent/i18n/es_CO.po
odoo_addons/mail_sent/i18n/fi.po
odoo_addons/mail_sent/i18n/fr.po
odoo_addons/mail_sent/i18n/id.po
odoo_addons/mail_sent/i18n/mail_sent.pot
odoo_addons/mail_sent/i18n/pt_BR.po
odoo_addons/mail_sent/i18n/sl.po
odoo_addons/mail_sent/static/description/icon.png
odoo_addons/mail_sent/static/description/icon.svg
odoo_addons/mail_sent/views/mail.xml
